opencv_fixer/__init__.py
opencv_fixer/autofix.py
opencv_fixer-0.2.5.dist-info/LICENSE
opencv_fixer-0.2.5.dist-info/METADATA
opencv_fixer-0.2.5.dist-info/WHEEL
opencv_fixer-0.2.5.dist-info/top_level.txt
opencv_fixer-0.2.5.dist-info/RECORD
