Metadata-Version: 2.1
Name: opencv-fixer
Version: 0.2.5
Summary: Fix OpenCV Issue for numpy, diffusers, etc.
Home-page: https://github.com/soulteary/opencv-fixer
Author: soulteary
Author-email: soulteary@gmail.com
License: Apache 2.0
License-File: LICENSE
